LICENSE
README.md
setup.py
ohnlp/__init__.py
ohnlp/toolkit/__init__.py
ohnlp/toolkit/backbone/__init__.py
ohnlp/toolkit/backbone/api.py
ohnlp/toolkit/backbone/backbone_module_launcher.py
ohnlptk_xlang_python.egg-info/PKG-INFO
ohnlptk_xlang_python.egg-info/SOURCES.txt
ohnlptk_xlang_python.egg-info/dependency_links.txt
ohnlptk_xlang_python.egg-info/requires.txt
ohnlptk_xlang_python.egg-info/top_level.txt