Metadata-Version: 2.1
Name: ohnlptk-xlang-python
Version: 2.0.1
Summary: Python support for OHNLP Toolkit Components
Author: Andrew Wen
Author-email: contact@ohnlp.org
Requires-Python: >3.7
License-File: LICENSE
